enderecobr-0.0.6.dist-info/METADATA
enderecobr-0.0.6.dist-info/WHEEL
enderecobr.libs/libgcc_s-0366c7ba.so.1
enderecobr/__init__.py
enderecobr/enderecobr.cpython-313t-arm-linux-musleabihf.so
enderecobr/enderecobr.pyi
enderecobr/py.typed
enderecobr/tests/test_geral.py
enderecobr-0.0.6.dist-info/RECORD
