Metadata-Version: 2.4
Name: enderecobr
Version: 0.0.6
Classifier: Programming Language :: Rust
Classifier: Programming Language :: Python :: Implementation :: CPython
Classifier: Programming Language :: Python :: Implementation :: PyPy
Classifier: Development Status :: 3 - Alpha
Classifier: Intended Audience :: Developers
Classifier: Intended Audience :: Education
Classifier: Intended Audience :: Science/Research
Classifier: Operating System :: OS Independent
Classifier: Programming Language :: Python :: 3
Classifier: Programming Language :: Python :: 3.8
Classifier: Programming Language :: Python :: 3.9
Classifier: Programming Language :: Python :: 3.10
Classifier: Programming Language :: Python :: 3.11
Classifier: Programming Language :: Python :: 3.12
Classifier: Programming Language :: Python :: 3.13
Classifier: License :: OSI Approved :: MIT License
Classifier: Natural Language :: Portuguese (Brazilian)
Classifier: Topic :: Scientific/Engineering :: Artificial Intelligence
Requires-Dist: mkdocstrings-python>=1.18.2 ; extra == 'doc'
Provides-Extra: doc
Summary: Bindings em Rust para padronizar endereços brasileiros
Keywords: address,brazil,brasil,regex,geocoding
Author-email: Daniel Herszenhut Meirelles Santos <daniel.santos@ipea.gov.br>, Gabriel Garcia de Almeida <gabriel.almeida@ipea.gov.br>, Rafael Henrique Moraes Pereira <rafael.pereira@ipea.gov.br>
Requires-Python: >=3.9
Project-URL: Homepage, https://github.com/ipeaGIT/enderecobr_rs
Project-URL: Source, https://github.com/ipeaGIT/enderecobr_rs
Project-URL: Documentation, https://enderecobr-py.readthedocs.io
Project-URL: Issues, https://github.com/ipeaGIT/enderecobr_rs/issues
